setup.py
zotero_word_items_to_collection.py
zotero_word_items_to_collection.egg-info/PKG-INFO
zotero_word_items_to_collection.egg-info/SOURCES.txt
zotero_word_items_to_collection.egg-info/dependency_links.txt
zotero_word_items_to_collection.egg-info/entry_points.txt
zotero_word_items_to_collection.egg-info/requires.txt
zotero_word_items_to_collection.egg-info/top_level.txt