Metadata-Version: 1.2
Name: zotero-word-items-to-collection
Version: 0.1
Summary: Create Zotero collections from Word files
Home-page: https://github.com/mwort/zotero_word_items_to_collection
Author: Michel Wortmann
Author-email: wortmann@pik-potsdam.de
License: MIT
Platform: UNKNOWN
Classifier: Development Status :: 3 - Alpha
Classifier: Programming Language :: Python :: 3
Classifier: License :: OSI Approved :: MIT License
Classifier: Topic :: Office/Business :: Office Suites
Classifier: Topic :: Scientific/Engineering
Requires-Python: >=3.5
